Metadata-Version: 2.1
Name: api-python-solar-forecast
Version: 0.1.0
Summary: api-python-solar-forecast
Author: Julio Martinez del Pino
Author-email: juliomdp92@gmail.com
Requires-Python: >=3.9,<3.13
Classifier: Programming Language :: Python :: 3
Classifier: Programming Language :: Python :: 3.9
Classifier: Programming Language :: Python :: 3.10
Classifier: Programming Language :: Python :: 3.11
Classifier: Programming Language :: Python :: 3.12
Requires-Dist: fastapi (==0.108.*)
Requires-Dist: python-decouple (==3.8)
Requires-Dist: uvicorn (==0.25.*)
